ice_launcher/__about__.py
ice_launcher/__init__.py
ice_launcher/__main__.py
ice_launcher/about.py
ice_launcher/accounts.py
ice_launcher/instances.py
ice_launcher/new_instance.py
ice_launcher/news.py
ice_launcher/settings.py
ice_launcher-0.0.2.dist-info/METADATA
ice_launcher-0.0.2.dist-info/WHEEL
ice_launcher-0.0.2.dist-info/licenses/LICENSE.txt
ice_launcher-0.0.2.dist-info/RECORD
