Metadata-Version: 2.1
Name: ice-launcher
Version: 0.0.2
Summary: An unofficial WIP Minecraft Launcher
Project-URL: Documentation, https://github.com/mq1/ice-launcher#readme
Project-URL: Issues, https://github.com/mq1/ice-launcher/issues
Project-URL: Source, https://github.com/mq1/ice-launcher
Author-email: Manuel Quarneti <manuelquarneti@gmail.com>
Classifier: Development Status :: 4 - Beta
Classifier: Programming Language :: Python
Classifier: Programming Language :: Python :: 3.10
Classifier: Programming Language :: Python :: Implementation :: CPython
Requires-Python: >=3.10
Requires-Dist: appdirs~=1.4.4
Requires-Dist: customtkinter~=4.5.5
Requires-Dist: minecraft-launcher-lib~=5.2
Requires-Dist: pillow~=9.2.0
Requires-Dist: requests~=2.28.1
